{
  "version": "7",
  "dialect": "postgresql",
  "entries": [
    {
      "idx": 0,
      "version": "7",
      "when": 1778897731937,
      "tag": "0000_kind_tomorrow_man",
      "breakpoints": true
    },
    {
      "idx": 1,
      "version": "7",
      "when": 1778911666955,
      "tag": "0001_bumpy_callisto",
      "breakpoints": true
    },
    {
      "idx": 2,
      "version": "7",
      "when": 1778920000000,
      "tag": "0002_quiet_proudstar",
      "breakpoints": true
    },
    {
      "idx": 3,
      "version": "7",
      "when": 1747785600000,
      "tag": "0003_perf_indexes",
      "breakpoints": true
    },
    {
      "idx": 4,
      "version": "7",
      "when": 1779859018355,
      "tag": "0004_special_lilandra",
      "breakpoints": true
    },
    {
      "idx": 5,
      "version": "7",
      "when": 1780025839236,
      "tag": "0005_third_omega_flight",
      "breakpoints": true
    }
  ]
}